quantrix/__init__.py
quantrix/modules.py
quantrix-1.0.4.dist-info/LICENSE
quantrix-1.0.4.dist-info/METADATA
quantrix-1.0.4.dist-info/WHEEL
quantrix-1.0.4.dist-info/entry_points.txt
quantrix-1.0.4.dist-info/RECORD
