Metadata-Version: 2.3
Name: QuantriX
Version: 1.0.4
Summary: This library provides tools for quantitative analysis in finance.
License: Copyright @ 2024-2025, Yaroslav Lyulko
Keywords: quantitative analysis,binomial model,brownion motion,random walk,brownion bridge
Author: Yaroslav Lyulko
Requires-Python: >= 3.8
Classifier: Development Status :: 3 - Alpha
Classifier: Intended Audience :: Financial and Insurance Industry
Classifier: Intended Audience :: Science/Research
Classifier: Programming Language :: Python :: 3.8
Classifier: Programming Language :: Python :: 3.9
Classifier: Programming Language :: Python :: 3.10
Classifier: Programming Language :: Python :: 3.11
Classifier: License :: OSI Approved :: MIT License
Classifier: Topic :: Office/Business :: Financial :: Investment
Classifier: Topic :: Software Development :: Libraries
Requires-Dist: numpy (>=1.23.5) ; python_version >= "3.8"
Requires-Dist: random2
